{
    "fluentMethods": true,
    "clientRootFolder": "",
    "relationships": [],
    "fields": [
        {
            "fieldName": "name",
            "fieldType": "String",
            "fieldValidateRules": [
                "required",
                "maxlength"
            ],
            "fieldValidateRulesMaxlength": "50"
        },
        {
            "fieldName": "email",
            "fieldType": "String",
            "fieldValidateRules": [
                "pattern"
            ],
            "fieldValidateRulesPattern": "^[a-zA-Z0-9_.+-]+@([a-zA-Z0-9][a-zA-Z0-9-]*[a-zA-Z0-9]*\\.)+[a-zA-Z]{2,}$"
        }
    ],
    "changelogDate": "20220905065658",
    "dto": "mapstruct",
    "searchEngine": "elasticsearch",
    "service": "serviceImpl",
    "entityTableName": "jhi_user",
    "jpaMetamodelFiltering": true,
    "pagination": "pagination"
}
